README.md
setup.cfg
setup.py
starlette_openapi/__init__.py
starlette_openapi.egg-info/PKG-INFO
starlette_openapi.egg-info/SOURCES.txt
starlette_openapi.egg-info/dependency_links.txt
starlette_openapi.egg-info/requires.txt
starlette_openapi.egg-info/top_level.txt