Metadata-Version: 1.0
Name: starlette-openapi
Version: 0.1
Summary: openapi for starlette
Home-page: https://github.com/zpdev/starlette-openapi
Author: zpzhou
Author-email: himoker@163.com
License: UNKNOWN
Platform: UNKNOWN
